[
  {
    "year": 2024,
    "monthly": [
      {
        "pnl": 209479.97,
        "pnlstr": "2.09L",
        "date": "0001-01-01T00:00:00",
        "weekday": "Monday",
        "charges": 0.0,
        "color": null
      },
      {
        "pnl": 376309.42,
        "pnlstr": "3.76L",
        "date": "0001-01-01T00:00:00",
        "weekday": "Tuesday",
        "charges": 0.0,
        "color": null
      },
      {
        "pnl": 0.0,
        "pnlstr": "",
        "date": "0001-01-01T00:00:00",
        "weekday": "Wednesday",
        "charges": 0.0,
        "color": null
      },
      {
        "pnl": -624827.11,
        "pnlstr": "-6.25L",
        "date": "0001-01-01T00:00:00",
        "weekday": "Thursday",
        "charges": 0.0,
        "color": null
      },
      {
        "pnl": 296339.31,
        "pnlstr": "2.96L",
        "date": "0001-01-01T00:00:00",
        "weekday": "Friday",
        "charges": 0.0,
        "color": null
      },
      {
        "pnl": 0.0,
        "pnlstr": "",
        "date": "0001-01-01T00:00:00",
        "weekday": "Saturday",
        "charges": 0.0,
        "color": null
      },
      {
        "pnl": 0.0,
        "pnlstr": "",
        "date": "0001-01-01T00:00:00",
        "weekday": "Sunday",
        "charges": 0.0,
        "color": null
      }
    ],
    "total": 257301.59000000003,
    "totalstr": "2.57L"
  }
]