{
  "capital": 0.0,
  "totaltradingdays": 40,
  "windays": 30,
  "lossdays": 10,
  "maxwinningstreakdays": 9,
  "maxlosingstreakdays": 2,
  "maxdddays": 26,
  "maxdddaysstr": "24/01/2024 to 19/02/2024",
  "rewardtorisk": 0.0,
  "winrate": 75.0,
  "lossrate": 25.0,
  "avgmonthlyprofit": -85368.76205650004,
  "totalprofit": -170737.52411300008,
  "maxprofitaday": 288546.22,
  "maxlossaday": -455310.42,
  "avgprofit_lossdaily": -2845.6255000000006,
  "avgprofitonprofitdays": 60423.14399999999,
  "avglossonlossdays": -198343.185,
  "maxdrawdown": 668220.075256,
  "maxdrawdownper": 0.0,
  "avgmonthlyprofitstr": "-85.37K",
  "totalprofitstr": "-1.71L",
  "maxprofitadaystr": "2.89L",
  "maxlossadaystr": "-4.55L",
  "avgprofit_lossdailystr": "-2.85K",
  "avgprofitonprofitdaysstr": "60.42K",
  "avglossonlossdaysstr": "-1.98L",
  "maxdrawdownstr": "6.68L",
  "expectancyratio": 0.0
}