[
  {
    "pnl": 2502.898898,
    "pnlstr": null,
    "date": "2024-02-05T00:00:00",
    "weekday": "Feb 2024",
    "charges": 0.0,
    "color": null
  },
  {
    "pnl": 21723.978157999998,
    "pnlstr": null,
    "date": "2024-02-06T00:00:00",
    "weekday": "Feb 2024",
    "charges": 0.0,
    "color": null
  },
  {
    "pnl": 47801.890258,
    "pnlstr": null,
    "date": "2024-02-07T00:00:00",
    "weekday": "Feb 2024",
    "charges": 0.0,
    "color": null
  },
  {
    "pnl": 36835.813201,
    "pnlstr": null,
    "date": "2024-02-08T00:00:00",
    "weekday": "Feb 2024",
    "charges": 0.0,
    "color": null
  },
  {
    "pnl": 36835.813201,
    "pnlstr": null,
    "date": "2024-02-09T00:00:00",
    "weekday": "Feb 2024",
    "charges": 0.0,
    "color": null
  },
  {
    "pnl": 36835.813201,
    "pnlstr": null,
    "date": "2024-02-10T00:00:00",
    "weekday": "Feb 2024",
    "charges": 0.0,
    "color": null
  },
  {
    "pnl": 36835.813201,
    "pnlstr": null,
    "date": "2024-02-11T00:00:00",
    "weekday": "Feb 2024",
    "charges": 0.0,
    "color": null
  },
  {
    "pnl": 36835.813201,
    "pnlstr": null,
    "date": "2024-02-12T00:00:00",
    "weekday": "Feb 2024",
    "charges": 0.0,
    "color": null
  },
  {
    "pnl": 58561.539915,
    "pnlstr": null,
    "date": "2024-02-13T00:00:00",
    "weekday": "Feb 2024",
    "charges": 0.0,
    "color": null
  },
  {
    "pnl": -96880.29012699999,
    "pnlstr": null,
    "date": "2024-02-14T00:00:00",
    "weekday": "Feb 2024",
    "charges": 0.0,
    "color": null
  },
  {
    "pnl": -87396.99322699998,
    "pnlstr": null,
    "date": "2024-02-15T00:00:00",
    "weekday": "Feb 2024",
    "charges": 0.0,
    "color": null
  },
  {
    "pnl": -65272.964857999985,
    "pnlstr": null,
    "date": "2024-02-16T00:00:00",
    "weekday": "Feb 2024",
    "charges": 0.0,
    "color": null
  },
  {
    "pnl": -65272.964857999985,
    "pnlstr": null,
    "date": "2024-02-17T00:00:00",
    "weekday": "Feb 2024",
    "charges": 0.0,
    "color": null
  },
  {
    "pnl": -65272.964857999985,
    "pnlstr": null,
    "date": "2024-02-18T00:00:00",
    "weekday": "Feb 2024",
    "charges": 0.0,
    "color": null
  },
  {
    "pnl": -33195.876134999984,
    "pnlstr": null,
    "date": "2024-02-19T00:00:00",
    "weekday": "Feb 2024",
    "charges": 0.0,
    "color": null
  },
  {
    "pnl": -28909.388477999986,
    "pnlstr": null,
    "date": "2024-02-20T00:00:00",
    "weekday": "Feb 2024",
    "charges": 0.0,
    "color": null
  },
  {
    "pnl": -20361.062252999986,
    "pnlstr": null,
    "date": "2024-02-21T00:00:00",
    "weekday": "Feb 2024",
    "charges": 0.0,
    "color": null
  },
  {
    "pnl": -83351.31284099999,
    "pnlstr": null,
    "date": "2024-02-22T00:00:00",
    "weekday": "Feb 2024",
    "charges": 0.0,
    "color": null
  },
  {
    "pnl": -62529.74565499999,
    "pnlstr": null,
    "date": "2024-02-23T00:00:00",
    "weekday": "Feb 2024",
    "charges": 0.0,
    "color": null
  },
  {
    "pnl": -62529.74565499999,
    "pnlstr": null,
    "date": "2024-02-24T00:00:00",
    "weekday": "Feb 2024",
    "charges": 0.0,
    "color": null
  },
  {
    "pnl": -62529.74565499999,
    "pnlstr": null,
    "date": "2024-02-25T00:00:00",
    "weekday": "Feb 2024",
    "charges": 0.0,
    "color": null
  },
  {
    "pnl": -35289.24655099999,
    "pnlstr": null,
    "date": "2024-02-26T00:00:00",
    "weekday": "Feb 2024",
    "charges": 0.0,
    "color": null
  },
  {
    "pnl": -8931.49155399999,
    "pnlstr": null,
    "date": "2024-02-27T00:00:00",
    "weekday": "Feb 2024",
    "charges": 0.0,
    "color": null
  },
  {
    "pnl": 18519.067759000012,
    "pnlstr": null,
    "date": "2024-02-28T00:00:00",
    "weekday": "Feb 2024",
    "charges": 0.0,
    "color": null
  },
  {
    "pnl": 42172.37373900002,
    "pnlstr": null,
    "date": "2024-02-29T00:00:00",
    "weekday": "Feb 2024",
    "charges": 0.0,
    "color": null
  },
  {
    "pnl": 71337.11837000001,
    "pnlstr": null,
    "date": "2024-03-01T00:00:00",
    "weekday": "Mar 2024",
    "charges": 0.0,
    "color": null
  },
  {
    "pnl": 71337.11837000001,
    "pnlstr": null,
    "date": "2024-03-02T00:00:00",
    "weekday": "Mar 2024",
    "charges": 0.0,
    "color": null
  },
  {
    "pnl": 71337.11837000001,
    "pnlstr": null,
    "date": "2024-03-03T00:00:00",
    "weekday": "Mar 2024",
    "charges": 0.0,
    "color": null
  },
  {
    "pnl": 124417.47536500002,
    "pnlstr": null,
    "date": "2024-03-04T00:00:00",
    "weekday": "Mar 2024",
    "charges": 0.0,
    "color": null
  },
  {
    "pnl": 137565.08526400002,
    "pnlstr": null,
    "date": "2024-03-05T00:00:00",
    "weekday": "Mar 2024",
    "charges": 0.0,
    "color": null
  },
  {
    "pnl": 165822.97876800003,
    "pnlstr": null,
    "date": "2024-03-06T00:00:00",
    "weekday": "Mar 2024",
    "charges": 0.0,
    "color": null
  },
  {
    "pnl": 167045.60228800002,
    "pnlstr": null,
    "date": "2024-03-07T00:00:00",
    "weekday": "Mar 2024",
    "charges": 0.0,
    "color": null
  },
  {
    "pnl": 167045.60228800002,
    "pnlstr": null,
    "date": "2024-03-08T00:00:00",
    "weekday": "Mar 2024",
    "charges": 0.0,
    "color": null
  },
  {
    "pnl": 167045.60228800002,
    "pnlstr": null,
    "date": "2024-03-09T00:00:00",
    "weekday": "Mar 2024",
    "charges": 0.0,
    "color": null
  },
  {
    "pnl": 167045.60228800002,
    "pnlstr": null,
    "date": "2024-03-10T00:00:00",
    "weekday": "Mar 2024",
    "charges": 0.0,
    "color": null
  },
  {
    "pnl": 207456.09431200003,
    "pnlstr": null,
    "date": "2024-03-11T00:00:00",
    "weekday": "Mar 2024",
    "charges": 0.0,
    "color": null
  },
  {
    "pnl": 148676.98373000004,
    "pnlstr": null,
    "date": "2024-03-12T00:00:00",
    "weekday": "Mar 2024",
    "charges": 0.0,
    "color": null
  },
  {
    "pnl": 167364.51568100005,
    "pnlstr": null,
    "date": "2024-03-13T00:00:00",
    "weekday": "Mar 2024",
    "charges": 0.0,
    "color": null
  },
  {
    "pnl": 196291.10357600005,
    "pnlstr": null,
    "date": "2024-03-14T00:00:00",
    "weekday": "Mar 2024",
    "charges": 0.0,
    "color": null
  },
  {
    "pnl": 215560.67781100006,
    "pnlstr": null,
    "date": "2024-03-15T00:00:00",
    "weekday": "Mar 2024",
    "charges": 0.0,
    "color": null
  },
  {
    "pnl": 215560.67781100006,
    "pnlstr": null,
    "date": "2024-03-16T00:00:00",
    "weekday": "Mar 2024",
    "charges": 0.0,
    "color": null
  },
  {
    "pnl": 215560.67781100006,
    "pnlstr": null,
    "date": "2024-03-17T00:00:00",
    "weekday": "Mar 2024",
    "charges": 0.0,
    "color": null
  },
  {
    "pnl": 116778.60975300006,
    "pnlstr": null,
    "date": "2024-03-18T00:00:00",
    "weekday": "Mar 2024",
    "charges": 0.0,
    "color": null
  },
  {
    "pnl": 126196.26411900006,
    "pnlstr": null,
    "date": "2024-03-19T00:00:00",
    "weekday": "Mar 2024",
    "charges": 0.0,
    "color": null
  },
  {
    "pnl": 74029.26393200006,
    "pnlstr": null,
    "date": "2024-03-20T00:00:00",
    "weekday": "Mar 2024",
    "charges": 0.0,
    "color": null
  },
  {
    "pnl": 91913.52307900006,
    "pnlstr": null,
    "date": "2024-03-21T00:00:00",
    "weekday": "Mar 2024",
    "charges": 0.0,
    "color": null
  },
  {
    "pnl": 120412.61250600006,
    "pnlstr": null,
    "date": "2024-03-22T00:00:00",
    "weekday": "Mar 2024",
    "charges": 0.0,
    "color": null
  },
  {
    "pnl": 120412.61250600006,
    "pnlstr": null,
    "date": "2024-03-23T00:00:00",
    "weekday": "Mar 2024",
    "charges": 0.0,
    "color": null
  },
  {
    "pnl": 120412.61250600006,
    "pnlstr": null,
    "date": "2024-03-24T00:00:00",
    "weekday": "Mar 2024",
    "charges": 0.0,
    "color": null
  },
  {
    "pnl": 120412.61250600006,
    "pnlstr": null,
    "date": "2024-03-25T00:00:00",
    "weekday": "Mar 2024",
    "charges": 0.0,
    "color": null
  },
  {
    "pnl": 133663.13722400006,
    "pnlstr": null,
    "date": "2024-03-26T00:00:00",
    "weekday": "Mar 2024",
    "charges": 0.0,
    "color": null
  },
  {
    "pnl": 203830.02545000007,
    "pnlstr": null,
    "date": "2024-03-27T00:00:00",
    "weekday": "Mar 2024",
    "charges": 0.0,
    "color": null
  },
  {
    "pnl": 273783.8812350001,
    "pnlstr": null,
    "date": "2024-03-28T00:00:00",
    "weekday": "Mar 2024",
    "charges": 0.0,
    "color": null
  },
  {
    "pnl": 273783.8812350001,
    "pnlstr": null,
    "date": "2024-03-29T00:00:00",
    "weekday": "Mar 2024",
    "charges": 0.0,
    "color": null
  },
  {
    "pnl": 273783.8812350001,
    "pnlstr": null,
    "date": "2024-03-30T00:00:00",
    "weekday": "Mar 2024",
    "charges": 0.0,
    "color": null
  },
  {
    "pnl": 273783.8812350001,
    "pnlstr": null,
    "date": "2024-03-31T00:00:00",
    "weekday": "Mar 2024",
    "charges": 0.0,
    "color": null
  },
  {
    "pnl": 352140.7195760001,
    "pnlstr": null,
    "date": "2024-04-01T00:00:00",
    "weekday": "Apr 2024",
    "charges": 0.0,
    "color": null
  },
  {
    "pnl": 376423.67378800013,
    "pnlstr": null,
    "date": "2024-04-02T00:00:00",
    "weekday": "Apr 2024",
    "charges": 0.0,
    "color": null
  },
  {
    "pnl": 403600.1074490001,
    "pnlstr": null,
    "date": "2024-04-03T00:00:00",
    "weekday": "Apr 2024",
    "charges": 0.0,
    "color": null
  },
  {
    "pnl": 339906.4644320001,
    "pnlstr": null,
    "date": "2024-04-04T00:00:00",
    "weekday": "Apr 2024",
    "charges": 0.0,
    "color": null
  },
  {
    "pnl": 389394.71861500014,
    "pnlstr": null,
    "date": "2024-04-05T00:00:00",
    "weekday": "Apr 2024",
    "charges": 0.0,
    "color": null
  },
  {
    "pnl": 389394.71861500014,
    "pnlstr": null,
    "date": "2024-04-06T00:00:00",
    "weekday": "Apr 2024",
    "charges": 0.0,
    "color": null
  },
  {
    "pnl": 389394.71861500014,
    "pnlstr": null,
    "date": "2024-04-07T00:00:00",
    "weekday": "Apr 2024",
    "charges": 0.0,
    "color": null
  },
  {
    "pnl": 398575.89292300015,
    "pnlstr": null,
    "date": "2024-04-08T00:00:00",
    "weekday": "Apr 2024",
    "charges": 0.0,
    "color": null
  },
  {
    "pnl": 345209.6053540002,
    "pnlstr": null,
    "date": "2024-04-09T00:00:00",
    "weekday": "Apr 2024",
    "charges": 0.0,
    "color": null
  },
  {
    "pnl": 397555.69173200015,
    "pnlstr": null,
    "date": "2024-04-10T00:00:00",
    "weekday": "Apr 2024",
    "charges": 0.0,
    "color": null
  },
  {
    "pnl": 397555.69173200015,
    "pnlstr": null,
    "date": "2024-04-11T00:00:00",
    "weekday": "Apr 2024",
    "charges": 0.0,
    "color": null
  },
  {
    "pnl": 405139.60467800015,
    "pnlstr": null,
    "date": "2024-04-12T00:00:00",
    "weekday": "Apr 2024",
    "charges": 0.0,
    "color": null
  },
  {
    "pnl": 405139.60467800015,
    "pnlstr": null,
    "date": "2024-04-13T00:00:00",
    "weekday": "Apr 2024",
    "charges": 0.0,
    "color": null
  },
  {
    "pnl": 405139.60467800015,
    "pnlstr": null,
    "date": "2024-04-14T00:00:00",
    "weekday": "Apr 2024",
    "charges": 0.0,
    "color": null
  },
  {
    "pnl": 422879.33323000016,
    "pnlstr": null,
    "date": "2024-04-15T00:00:00",
    "weekday": "Apr 2024",
    "charges": 0.0,
    "color": null
  },
  {
    "pnl": 451948.3107810002,
    "pnlstr": null,
    "date": "2024-04-16T00:00:00",
    "weekday": "Apr 2024",
    "charges": 0.0,
    "color": null
  },
  {
    "pnl": 451948.3107810002,
    "pnlstr": null,
    "date": "2024-04-17T00:00:00",
    "weekday": "Apr 2024",
    "charges": 0.0,
    "color": null
  },
  {
    "pnl": 643245.9205240002,
    "pnlstr": null,
    "date": "2024-04-18T00:00:00",
    "weekday": "Apr 2024",
    "charges": 0.0,
    "color": null
  },
  {
    "pnl": 582479.9647400002,
    "pnlstr": null,
    "date": "2024-04-19T00:00:00",
    "weekday": "Apr 2024",
    "charges": 0.0,
    "color": null
  },
  {
    "pnl": 582479.9647400002,
    "pnlstr": null,
    "date": "2024-04-20T00:00:00",
    "weekday": "Apr 2024",
    "charges": 0.0,
    "color": null
  },
  {
    "pnl": 582479.9647400002,
    "pnlstr": null,
    "date": "2024-04-21T00:00:00",
    "weekday": "Apr 2024",
    "charges": 0.0,
    "color": null
  },
  {
    "pnl": 574950.4682590002,
    "pnlstr": null,
    "date": "2024-04-22T00:00:00",
    "weekday": "Apr 2024",
    "charges": 0.0,
    "color": null
  },
  {
    "pnl": 544396.2753860002,
    "pnlstr": null,
    "date": "2024-04-23T00:00:00",
    "weekday": "Apr 2024",
    "charges": 0.0,
    "color": null
  },
  {
    "pnl": 546711.2720880002,
    "pnlstr": null,
    "date": "2024-04-24T00:00:00",
    "weekday": "Apr 2024",
    "charges": 0.0,
    "color": null
  },
  {
    "pnl": 479267.06509900023,
    "pnlstr": null,
    "date": "2024-04-25T00:00:00",
    "weekday": "Apr 2024",
    "charges": 0.0,
    "color": null
  },
  {
    "pnl": 489254.1792130002,
    "pnlstr": null,
    "date": "2024-04-26T00:00:00",
    "weekday": "Apr 2024",
    "charges": 0.0,
    "color": null
  }
]