[
  {
    "year": 2024,
    "monthly": [
      {
        "pnl": -347.75,
        "pnlstr": "-347.75",
        "date": "0001-01-01T00:00:00",
        "weekday": "Monday",
        "charges": 0.0,
        "color": null
      },
      {
        "pnl": 0.0,
        "pnlstr": "",
        "date": "0001-01-01T00:00:00",
        "weekday": "Tuesday",
        "charges": 0.0,
        "color": null
      },
      {
        "pnl": 0.0,
        "pnlstr": "",
        "date": "0001-01-01T00:00:00",
        "weekday": "Wednesday",
        "charges": 0.0,
        "color": null
      },
      {
        "pnl": -342.78000000000003,
        "pnlstr": "-342.78",
        "date": "0001-01-01T00:00:00",
        "weekday": "Thursday",
        "charges": 0.0,
        "color": null
      },
      {
        "pnl": 30250.65,
        "pnlstr": "30.25K",
        "date": "0001-01-01T00:00:00",
        "weekday": "Friday",
        "charges": 0.0,
        "color": null
      },
      {
        "pnl": 0.0,
        "pnlstr": "",
        "date": "0001-01-01T00:00:00",
        "weekday": "Saturday",
        "charges": 0.0,
        "color": null
      },
      {
        "pnl": 0.0,
        "pnlstr": "",
        "date": "0001-01-01T00:00:00",
        "weekday": "Sunday",
        "charges": 0.0,
        "color": null
      }
    ],
    "total": 29560.120000000003,
    "totalstr": "29.56K"
  }
]