[
  {
    "pnl": 0.0,
    "date": "2024-02-23T00:00:00",
    "weekday": "Feb 2024",
    "netpnl": 99694.256579
  },
  {
    "pnl": 0.0,
    "date": "2024-02-24T00:00:00",
    "weekday": "Feb 2024",
    "netpnl": 99694.256579
  },
  {
    "pnl": 0.0,
    "date": "2024-02-25T00:00:00",
    "weekday": "Feb 2024",
    "netpnl": 99694.256579
  },
  {
    "pnl": 0.0,
    "date": "2024-02-26T00:00:00",
    "weekday": "Feb 2024",
    "netpnl": 141221.542674
  },
  {
    "pnl": -10236.060681999996,
    "date": "2024-02-27T00:00:00",
    "weekday": "Feb 2024",
    "netpnl": 130985.481992
  }
]