[
  {
    "pnl": -101030.667764,
    "pnlstr": null,
    "date": "2024-02-03T00:00:00",
    "weekday": "Feb 2024",
    "charges": 0.0,
    "color": null
  },
  {
    "pnl": -8872.680104000028,
    "pnlstr": null,
    "date": "2024-02-10T00:00:00",
    "weekday": "Feb 2024",
    "charges": 0.0,
    "color": null
  },
  {
    "pnl": -90270.59598200004,
    "pnlstr": null,
    "date": "2024-02-17T00:00:00",
    "weekday": "Feb 2024",
    "charges": 0.0,
    "color": null
  },
  {
    "pnl": -97138.43489700003,
    "pnlstr": null,
    "date": "2024-02-24T00:00:00",
    "weekday": "Feb 2024",
    "charges": 0.0,
    "color": null
  },
  {
    "pnl": 0.0,
    "pnlstr": null,
    "date": "2024-03-02T00:00:00",
    "weekday": "Mar 2024",
    "charges": 0.0,
    "color": null
  },
  {
    "pnl": 0.0,
    "pnlstr": null,
    "date": "2024-03-09T00:00:00",
    "weekday": "Mar 2024",
    "charges": 0.0,
    "color": null
  },
  {
    "pnl": 0.0,
    "pnlstr": null,
    "date": "2024-03-16T00:00:00",
    "weekday": "Mar 2024",
    "charges": 0.0,
    "color": null
  },
  {
    "pnl": -51381.74279100001,
    "pnlstr": null,
    "date": "2024-03-23T00:00:00",
    "weekday": "Mar 2024",
    "charges": 0.0,
    "color": null
  },
  {
    "pnl": 0.0,
    "pnlstr": null,
    "date": "2024-03-30T00:00:00",
    "weekday": "Mar 2024",
    "charges": 0.0,
    "color": null
  }
]